pgh/__init__.py
pgh/check.py
pygame_gui_helper-0.0.2.dist-info/LICENSE
pygame_gui_helper-0.0.2.dist-info/METADATA
pygame_gui_helper-0.0.2.dist-info/WHEEL
pygame_gui_helper-0.0.2.dist-info/top_level.txt
pygame_gui_helper-0.0.2.dist-info/RECORD
