Metadata-Version: 2.1
Name: pygame-gui-helper
Version: 0.0.2
Summary: GUI for "pygame"
Author-email: Strexas <kirsnauskas1@gmail.com>
License: MIT License        
Classifier: Programming Language :: Python :: 3
Classifier: License :: OSI Approved :: MIT License
Classifier: Operating System :: OS Independent
Requires-Python: >=3.7
License-File: LICENSE
